pic2vec/__init__.py
pic2vec/build_featurizer.py
pic2vec/data_featurizing.py
pic2vec/enums.py
pic2vec/feature_preprocessing.py
pic2vec/image_featurizer.py
pic2vec/squeezenet.py
pic2vec/saved_models/squeezenet_weights_tf_dim_ordering_tf_kernels.h5
pic2vec-0.101.1.dist-info/AUTHORS.rst
pic2vec-0.101.1.dist-info/LICENSE
pic2vec-0.101.1.dist-info/METADATA
pic2vec-0.101.1.dist-info/WHEEL
pic2vec-0.101.1.dist-info/top_level.txt
pic2vec-0.101.1.dist-info/RECORD
