Metadata-Version: 2.1
Name: pic2vec
Version: 0.101.1
Summary: Featurize images using a decapitated, pre-trained deep learning network
Home-page: https://github.com/datarobot/pic2vec
Author: Jett Oristaglio
Author-email: jettori88@gmail.com
License: BSD license
Keywords: image_featurizer,featurize,pic2vec
Platform: UNKNOWN
Classifier: Development Status :: 3 - Alpha
Classifier: Intended Audience :: Developers
Classifier: License :: OSI Approved :: BSD License
Classifier: Natural Language :: English
Classifier: Programming Language :: Python :: 2.7
Classifier: Programming Language :: Python :: 3.4
Classifier: Programming Language :: Python :: 3.5
Classifier: Programming Language :: Python :: 3.6
Classifier: Programming Language :: Python :: 3.7
Requires-Dist: h5py (<3,>=2.7.0)
Requires-Dist: scipy (<2,>=1.1)
Requires-Dist: numpy (<2,>=1.15.4)
Requires-Dist: tensorflow (<2,>=1.2.0)
Requires-Dist: keras (<2.3.0,>=2.2.3)
Requires-Dist: pandas (<1,>=0.20.2)
Requires-Dist: Pillow (<6,>=5.4.1)
Requires-Dist: trafaret (<2,>=1)
